waveletnn/__init__.py
waveletnn/biorthogonal.py
waveletnn/inverse.py
waveletnn/losses.py
waveletnn/orthonormal.py
waveletnn/padding.py
waveletnn-0.3.4.dist-info/LICENSE
waveletnn-0.3.4.dist-info/METADATA
waveletnn-0.3.4.dist-info/WHEEL
waveletnn-0.3.4.dist-info/RECORD
