Metadata-Version: 2.3
Name: waveletnn
Version: 0.3.4
Summary: WaveletNN blocks and losses
License: MIT
Keywords: wavelet,dwt,idwt,pytorch
Author: Scurrra (Ilja Baroŭski)
Author-email: iscurrra@gmail.com
Requires-Python: >=3.11
Classifier: Programming Language :: Python :: 3
Classifier: Development Status :: 4 - Beta
Provides-Extra: pywt
Requires-Dist: PyWavelets ; extra == "pywt"
Requires-Dist: numpy
Requires-Dist: torch (>=2)
Project-URL: Issues, https://github.com/Scurrra/WaveletNN-PyTorch/issues
Project-URL: Repository, https://github.com/Scurrra/WaveletNN-PyTorch.git
